<?xml version="1.0" encoding="utf-8" ?><dwsync><file name="app_0050.js" server="develop.flvs.net/collaborate/reinvention/take_a_stand/" local="3490701450" remote="318763443883539372" Dst="-1" /><file name="bootstrap.css" server="develop.flvs.net/collaborate/reinvention/take_a_stand/" local="3490701452" remote="318763443883097652" Dst="-1" /><file name="data.js" server="develop.flvs.net/collaborate/reinvention/take_a_stand/" local="3490701454" remote="318763443883097712" Dst="-1" /><file name="handlebars-v1.3.0.js" server="develop.flvs.net/collaborate/reinvention/take_a_stand/" local="3490701456" remote="318763443883162572" Dst="-1" /><file name="index.html" server="develop.flvs.net/collaborate/reinvention/take_a_stand/" local="3490701460" remote="318763443883539432" Dst="-1" /><file name="index_validation_page.html" server="develop.flvs.net/collaborate/reinvention/take_a_stand/" local="3490701460" remote="318763443883184772" Dst="-1" /><file name="template_0300.html" server="develop.flvs.net/collaborate/reinvention/take_a_stand/" local="3490701461" remote="318763443883100772" Dst="-1" /><file name="template_0400.html" server="develop.flvs.net/collaborate/reinvention/take_a_stand/" local="3490701461" remote="318763443883097772" Dst="-1" /><file name="template_0600.html" server="develop.flvs.net/collaborate/reinvention/take_a_stand/" local="3490701461" remote="318763443883100772" Dst="-1" /><file name="template_0900.html" server="develop.flvs.net/collaborate/reinvention/take_a_stand/" local="3490701461" remote="318763443883097772" Dst="-1" /><file name="template_1000.html" server="develop.flvs.net/collaborate/reinvention/take_a_stand/" local="3490701462" remote="318763443883101012" Dst="-1" /></dwsync>